samplemaker/__init__.py
samplemaker/baselib/__init__.py
samplemaker/baselib/devices.py
samplemaker/baselib/waveguides.py
samplemaker/devices.py
samplemaker/documentation.md
samplemaker/gdsreader.py
samplemaker/gdswriter.py
samplemaker/layout.py
samplemaker/makers.py
samplemaker/phc.py
samplemaker/resources/__init__.py
samplemaker/resources/boopy.cp311-win_amd64.pyd
samplemaker/resources/boopy.pyi
samplemaker/resources/sm_stencil_font.txt
samplemaker/routers.py
samplemaker/sequencer.py
samplemaker/shapes.py
samplemaker/viewers.py
samplemaker_sparrow-5.4.6.dist-info/METADATA
samplemaker_sparrow-5.4.6.dist-info/WHEEL
samplemaker_sparrow-5.4.6.dist-info/licenses/LICENSE.md
samplemaker_sparrow-5.4.6.dist-info/RECORD
