Metadata-Version: 2.4
Name: samplemaker-sparrow
Version: 5.4.6
Summary: Lithographic mask design package
Author-Email: Leonardo Midolo <midolo@nbi.ku.dk>, Jeppe Roulund <jeppe.roulund@sparrowquantum.com>
License-Expression: BSD-3-Clause
License-File: LICENSE.md
Classifier: Programming Language :: C++
Classifier: Programming Language :: Python
Classifier: Programming Language :: Python :: 3
Classifier: Programming Language :: Python :: 3 :: Only
Classifier: Programming Language :: Python :: 3.10
Classifier: Programming Language :: Python :: 3.11
Classifier: Programming Language :: Python :: 3.12
Classifier: Programming Language :: Python :: 3.13
Classifier: Operating System :: Microsoft :: Windows
Classifier: Operating System :: MacOS
Classifier: Operating System :: Unix
Classifier: Operating System :: POSIX :: Linux
Project-URL: Repository, https://github.com/SparrowQuantum/samplemaker.git
Requires-Python: <3.14,>=3.10
Requires-Dist: matplotlib>=3.7.5
Requires-Dist: numpy==2.*
